markdown_live_preview/__init__.py
markdown_live_preview/__main__.py
markdown_live_preview/js/__init__.py
markdown_live_preview/js/index.html
markdown_live_preview/js/main.js
markdown_live_preview/js/mermaid.js
markdown_live_preview/js/site.css
markdown_live_preview/server/__init__.py
markdown_live_preview/server/__main__.py
markdown_live_preview/server/consts.py
markdown_live_preview/server/lexers.py
markdown_live_preview/server/log.py
markdown_live_preview/server/render.py
markdown_live_preview/server/server.py
markdown_live_preview/server/watch.py
markdown_live_preview-0.2.69.dist-info/METADATA
markdown_live_preview-0.2.69.dist-info/WHEEL
markdown_live_preview-0.2.69.dist-info/entry_points.txt
markdown_live_preview-0.2.69.dist-info/top_level.txt
markdown_live_preview-0.2.69.dist-info/RECORD
