Metadata-Version: 2.1
Name: markdown-live-preview
Version: 0.2.69
Summary: live web preview of markdown docs
Author-email: ms-jpq <github@bigly.dog>
Project-URL: homepage, https://github.com/ms-jpq/markdown-live-preview
Requires-Python: >=3.9.0
Requires-Dist: Markdown==3.7
Requires-Dist: Pygments==2.18.0
Requires-Dist: aiohttp==3.10.5
Requires-Dist: pymdown-extensions==10.9
Requires-Dist: watchdog==5.0.2
Provides-Extra: dev
Requires-Dist: mypy; extra == "dev"
Requires-Dist: types-Markdown; extra == "dev"
Requires-Dist: black; extra == "dev"
Requires-Dist: isort; extra == "dev"
Provides-Extra: dist
Requires-Dist: setuptools; extra == "dist"
Requires-Dist: wheel; extra == "dist"
